him_lychee-0.2.4.dist-info/licenses/LICENSE
lychee/__init__.py
him_lychee-0.2.4.dist-info/METADATA
him_lychee-0.2.4.dist-info/WHEEL
him_lychee-0.2.4.dist-info/top_level.txt
him_lychee-0.2.4.dist-info/RECORD
