Metadata-Version: 2.4
Name: him-lychee
Version: 0.2.4
Summary: Lychee Language Core: A lightweight, high-performance library for slang translation and NLP text cleaning (pre-processing).
Home-page: https://github.com/Himpadpa2004/him-lychee-language-core
Author: Himpadma "Him"
Author-email: himpadma2004@gmail.com
Classifier: Programming Language :: Python :: 3
Classifier: Programming Language :: Python :: 3.7
Classifier: Programming Language :: Python :: 3.8
Classifier: Programming Language :: Python :: 3.9
Classifier: Programming Language :: Python :: 3.10
Classifier: Programming Language :: Python :: 3.11
Classifier: Programming Language :: Python :: 3.12
Classifier: License :: OSI Approved :: MIT License
Classifier: Operating System :: OS Independent
Requires-Python: >=3.7
License-File: LICENSE
Requires-Dist: textblob
Requires-Dist: nltk
Requires-Dist: emoji
Requires-Dist: spacy
Provides-Extra: nlp
Requires-Dist: spacy[lookups]>=3.0; extra == "nlp"
Requires-Dist: textblob; extra == "nlp"
Requires-Dist: emoji; extra == "nlp"
Dynamic: license-file
